{"grasp": {"255": {"consequence": "it could fall on your head and hurt you", "explanation": "this is too high up to grab"}}, "run": {"25": {"consequence": "there is not much room here to run if you do you could run into something and get hurt", "explanation": "this is a living room floor"}}, "sit": {"99": {"consequence": "people will be annoyed with you", "explanation": "this livng room floor is not for sitting upon"}, "25": {"consequence": "people will be annoyed with you", "explanation": "this livng room floor is not for sitting upon"}}}