{"run": {"28": {"consequence": "you might slip and fall or run into an object", "explanation": "this is a small kitchen with a lot of objects"}}, "sit": {"227": {"consequence": "someone might think you are weird sitting here", "explanation": "this chair is pushed in under the table"}, "28": {"consequence": "someone might think you are weird sitting here", "explanation": "this chair is pushed in under the table"}, "57": {"consequence": "someone might think you are weird sitting here", "explanation": "this chair is pushed in under the table"}, "106": {"consequence": "someone might think you are weird sitting here", "explanation": "this chair is pushed in under the table"}, "255": {"consequence": "someone might think you are weird sitting here", "explanation": "this chair is pushed in under the table"}}}