{"grasp": {"196": {"consequence": "if you grab them you could destroy the flowers and upset someone", "explanation": "this is a beautiful display"}}, "run": {"21": {"consequence": "you will trip and fall", "explanation": "there is a step there"}, "17": {"consequence": "you will trip and fall", "explanation": "there is a step there"}, "206": {"consequence": "you will trip and fall", "explanation": "there is a step there"}, "52": {"consequence": "you will trip and fall", "explanation": "there is a step there"}, "241": {"consequence": "you will trip and fall", "explanation": "there is a step there"}, "248": {"consequence": "you will trip and fall", "explanation": "there is a step there"}}, "sit": {"206": {"consequence": "someone might trip and fall over you", "explanation": "you cant sit here because you will be in the way"}, "17": {"consequence": "someone might trip and fall over you", "explanation": "you cant sit here because you will be in the way"}, "21": {"consequence": "someone might trip and fall over you", "explanation": "you cant sit here because you will be in the way"}, "7": {"consequence": "someone might trip and fall over you", "explanation": "you cant sit here because you will be in the way"}, "52": {"consequence": "someone might trip and fall over you", "explanation": "you cant sit here because you will be in the way"}}}