{"grasp": {"175": {"consequence": "if you grasp this you may be ask to leave", "explanation": "it is improper to grasp something in someones home without permission"}, "143": {"consequence": "if you grasp this you may be ask to leave", "explanation": "it is improper to grasp something in someones home without permission"}, "239": {"consequence": "if you grasp this you may be ask to leave", "explanation": "it is improper to grasp something in someones home without permission"}}, "run": {"64": {"consequence": "you may crash into the table or other furniture in the room", "explanation": "it is too small an area to run"}}}