{"run": {"168": {"consequence": "the tables fall down", "explanation": "there is glass everywhere"}}, "sit": {"31": {"consequence": "you could fall off", "explanation": "the bar is high and narrow"}, "219": {"consequence": "you could fall off", "explanation": "the bar is high and narrow"}, "122": {"consequence": "you could fall off", "explanation": "the bar is high and narrow"}, "143": {"consequence": "you could fall off", "explanation": "the bar is high and narrow"}, "163": {"consequence": "you could fall off", "explanation": "the bar is high and narrow"}}}