{"grasp": {"213": {"consequence": "you will make the owner of the cushion unhappy", "explanation": "that does not belong to you"}}, "run": {"21": {"consequence": "and you would trip on things", "explanation": "the room is cluttered"}}, "sit": {"85": {"consequence": "if you sit here you will crush whatever is already there", "explanation": "there is already something in this area"}, "64": {"consequence": "if you sit here you will crush whatever is already there", "explanation": "there is already something in this area"}, "21": {"consequence": "if you sit here you will crush whatever is already there", "explanation": "there is already something in this area"}, "43": {"consequence": "if you sit here you will crush whatever is already there", "explanation": "there is already something in this area"}}}