{"run": {"30": {"consequence": "you could get hit by a car", "explanation": "it is dangerous to run on a bridge"}}, "sit": {"8": {"consequence": "you would be yelled at by every driver", "explanation": "the road is to travel inland on one side of the river"}, "30": {"consequence": "you would be yelled at by every driver", "explanation": "the road is to travel inland on one side of the river"}, "15": {"consequence": "you would be yelled at by every driver", "explanation": "the road is to travel inland on one side of the river"}, "23": {"consequence": "you would be yelled at by every driver", "explanation": "the road is to travel inland on one side of the river"}}}