{"grasp": {"159": {"consequence": "its glass and could break", "explanation": "it could fall on you"}, "128": {"consequence": "its glass and could break", "explanation": "it could fall on you"}, "112": {"consequence": "its glass and could break", "explanation": "it could fall on you"}, "223": {"consequence": "its glass and could break", "explanation": "it could fall on you"}, "96": {"consequence": "its glass and could break", "explanation": "it could fall on you"}}, "run": {"48": {"consequence": "you would bump into the bar or the chairs", "explanation": "there isnt room to run"}}, "sit": {"48": {"consequence": "people will think youre weird for not sitting in a chair", "explanation": "there are several empty chairs in this area"}}}