{"run": {"204": {"consequence": "you will hit them", "explanation": "there are people"}, "17": {"consequence": "you will hit them", "explanation": "there are people"}, "51": {"consequence": "you will hit them", "explanation": "there are people"}, "238": {"consequence": "you will hit them", "explanation": "there are people"}, "68": {"consequence": "you will hit them", "explanation": "there are people"}, "221": {"consequence": "you will hit them", "explanation": "there are people"}, "255": {"consequence": "you will hit them", "explanation": "there are people"}}, "sit": {"17": {"consequence": "you will get kicked out", "explanation": "it is forbidden to sit on the floor"}, "34": {"consequence": "you will get kicked out", "explanation": "it is forbidden to sit on the floor"}}}