{"grasp": {"206": {"consequence": "if you grasp this you may be ask to leave", "explanation": "it is improper to grasp something in someones home without permission"}, "194": {"consequence": "if you grasp this you may be ask to leave", "explanation": "it is improper to grasp something in someones home without permission"}, "219": {"consequence": "if you grasp this you may be ask to leave", "explanation": "it is improper to grasp something in someones home without permission"}, "182": {"consequence": "if you grasp this you may be ask to leave", "explanation": "it is improper to grasp something in someones home without permission"}, "243": {"consequence": "if you grasp this you may be ask to leave", "explanation": "it is improper to grasp something in someones home without permission"}, "170": {"consequence": "if you grasp this you may be ask to leave", "explanation": "it is improper to grasp something in someones home without permission"}}, "run": {"36": {"consequence": "you will run into the furniture", "explanation": "this is under a bed there"}}}