{"run": {"29": {"consequence": "you will fall and get hurt", "explanation": "this aisleway is too narrow for running"}}, "sit": {"216": {"consequence": "people will be angry that you are blocking the stairway", "explanation": "these are the stairs where people walk"}, "59": {"consequence": "people will be angry that you are blocking the stairway", "explanation": "these are the stairs where people walk"}, "29": {"consequence": "people will be angry that you are blocking the stairway", "explanation": "these are the stairs where people walk"}}}