{"run": {"16": {"consequence": "you would bother the people around you", "explanation": "you shouldnt run here because of the picnic tables being in the way"}}, "sit": {"177": {"consequence": "you might injure the person sitting in the chair", "explanation": "someone is sitting in this chair"}, "165": {"consequence": "you might injure the person sitting in the chair", "explanation": "someone is sitting in this chair"}, "16": {"consequence": "you might injure the person sitting in the chair", "explanation": "someone is sitting in this chair"}}}