{"grasp": {"166": {"consequence": "if you grasp this without permission you may be ask to leave", "explanation": "it is improper to grasp something in public without permission"}, "191": {"consequence": "if you grasp this without permission you may be ask to leave", "explanation": "it is improper to grasp something in public without permission"}, "179": {"consequence": "if you grasp this without permission you may be ask to leave", "explanation": "it is improper to grasp something in public without permission"}}, "run": {"64": {"consequence": "if you run you could hurt the people", "explanation": "you shouldnt run here there are people in the way"}}, "sit": {"64": {"consequence": "the two people will step on you", "explanation": "it is forbidden to sit on the floor"}}}