{"run": {"55": {"consequence": "you could trip and fall", "explanation": "becuase you are right by the stairway"}, "48": {"consequence": "you could trip and fall", "explanation": "becuase you are right by the stairway"}, "193": {"consequence": "you could trip and fall", "explanation": "becuase you are right by the stairway"}}, "sit": {"55": {"consequence": "you never know when people will need to use the stairs and you will be blocking them from doing so", "explanation": "this is the staircase"}, "165": {"consequence": "you never know when people will need to use the stairs and you will be blocking them from doing so", "explanation": "this is the staircase"}, "152": {"consequence": "you never know when people will need to use the stairs and you will be blocking them from doing so", "explanation": "this is the staircase"}, "193": {"consequence": "you never know when people will need to use the stairs and you will be blocking them from doing so", "explanation": "this is the staircase"}, "48": {"consequence": "you never know when people will need to use the stairs and you will be blocking them from doing so", "explanation": "this is the staircase"}}}