{"grasp": {"128": {"consequence": "if you grasp this without permission you may be ask to leave", "explanation": "it is improper to grasp something in public without permission"}, "145": {"consequence": "if you grasp this without permission you may be ask to leave", "explanation": "it is improper to grasp something in public without permission"}, "238": {"consequence": "if you grasp this without permission you may be ask to leave", "explanation": "it is improper to grasp something in public without permission"}, "136": {"consequence": "if you grasp this without permission you may be ask to leave", "explanation": "it is improper to grasp something in public without permission"}, "179": {"consequence": "if you grasp this without permission you may be ask to leave", "explanation": "it is improper to grasp something in public without permission"}}, "run": {"26": {"consequence": "you could get swiftly escorted out from the premises", "explanation": "robbie it is socially prohibited en to run around on any public building indoors high foot traffic floor"}}, "sit": {"26": {"consequence": "you could get stepped on by all the people walking around", "explanation": "the floor is not a place to sit"}}}